mle_core/__init__.py
mle_core/config.py
mle_core/chat/__init__.py
mle_core/chat/chat_service.py
mle_core/checkers/__init__.py
mle_core/checkers/fact_checker.py
mle_core/checkers/grammar.py
mle_core/checkers/hyperbole_detector.py
mle_core/checkers/neo4j_consistency.py
mle_core/checkers/prompts.py
mle_core/connectors/__init__.py
mle_core/connectors/base.py
mle_core/connectors/db/__init__.py
mle_core/connectors/db/mongo_connector.py
mle_core/connectors/db/neo4j_connector.py
mle_core/connectors/db/postgres_connector.py
mle_core/connectors/llm/__init__.py
mle_core/connectors/llm/anthropic_connector.py
mle_core/connectors/llm/azure_connector.py
mle_core/connectors/llm/base.py
mle_core/connectors/llm/openai_connector.py
mle_core/evaluators/__init__.py
mle_core/evaluators/functions.py
mle_core/evaluators/test_results_generation.py
mle_core/prompts/main.py
mle_core/utils/__init__.py
mle_core/utils/formatting.py
mle_core/utils/logging.py
mle_core/utils/response_handling.py
scripts/__init__.py
tests/__init__.py
tests/test_chat_module.py
tests/test_connector.py
tests/test_fact_checker.py
mle_core-0.1.0.dist-info/LICENSE
mle_core-0.1.0.dist-info/METADATA
mle_core-0.1.0.dist-info/WHEEL
mle_core-0.1.0.dist-info/top_level.txt
mle_core-0.1.0.dist-info/RECORD
