Metadata-Version: 2.1
Name: mle_core
Version: 0.1.0
Summary: Core modules necessary during application development
Home-page: https://github.com/RamailoTech/mle_core
Author: ML Experts Team
Author-email: mvp@ramailo.tech
Project-URL: Homepage, https://github.com/RamailoTech/mle_core
Project-URL: Issues, https://github.com/RamailoTech/mle_core/issues
Classifier: Programming Language :: Python :: 3
Classifier: License :: OSI Approved :: MIT License
Classifier: Operating System :: OS Independent
Requires-Python: >=3.9
License-File: LICENSE
Requires-Dist: sqlalchemy
Requires-Dist: pymongo
Requires-Dist: openai
Requires-Dist: requests
Requires-Dist: psycopg2-binary
Requires-Dist: python-dotenv
Requires-Dist: langchain
Requires-Dist: langchain-openai
Requires-Dist: langchain-community
Requires-Dist: pytest
Requires-Dist: pytest-asyncio
Requires-Dist: langchain-anthropic
Requires-Dist: neo4j==5.22.0
Requires-Dist: dspy-ai==2.4.12
Requires-Dist: language-tool-python==2.8
